mlog_util/__init__.py
mlog_util/handlers.old.py
mlog_util/handlers.py
mlog_util/log_manager.py
mlog_util-2025.12.23.dist-info/METADATA
mlog_util-2025.12.23.dist-info/WHEEL
mlog_util-2025.12.23.dist-info/top_level.txt
mlog_util-2025.12.23.dist-info/RECORD
