Metadata-Version: 2.4
Name: mlog-util
Version: 2025.12.23
Summary: Add your description here
Requires-Python: >=3.11
Requires-Dist: rich>=14.2.0
Requires-Dist: portalocker
